data_trans_functions/__init__.py
data_trans_functions/functions.py
data_trans_functions/py.typed
data_trans_functions-1.0.0.dist-info/METADATA
data_trans_functions-1.0.0.dist-info/WHEEL
data_trans_functions-1.0.0.dist-info/RECORD
