Metadata-Version: 2.1
Name: data-trans-functions
Version: 1.0.0
Summary: Implementation of three functions used in data transformation: matrix transpose, time series windowing and cross-correlation.
Author: Tadas
Author-email: tadas222@gmail.com
Requires-Python: >=3.10
Classifier: Programming Language :: Python :: 3
Classifier: Programming Language :: Python :: 3.10
Classifier: Programming Language :: Python :: 3.11
